[{"HabitatId": "ES_pub0201_Area_5", "HabitatTag": "ES_pub0201_Area_0", "HabitatKey": "pub0201_EN_ES_pub0201_Area_0", "RelativeLocation": {"X": 29750.0, "Y": 5670.0, "Z": 1120.0}, "Data": {"id": "ES_pub0201_Area_5", "members": [{"EnemyId": "E027_03_00_03001", "MinLv": 47, "MaxLv": 47, "Name": {"id": 271, "ja_JP": "\u30a2\u30fc\u30b9\u30a8\u30ec\u30e1\u30f3\u30c8", "zh_CN": "\u5730\u5143\u7d20\u7cbe\u7075"}, "Drops": [{"content_id": "pub0201", "id": 154000000, "drop_rate": 1428, "name": {"id": 9836, "ja_JP": "\u52d5\u7684\u30a8\u30f3\u30b0\u30e9\u30e0\u306e\u6b20\u7247", "zh_CN": "\u53d8\u5316\u7684\u80fd\u91cf\u788e\u7247"}}, {"content_id": "pub0201", "id": 154100000, "drop_rate": 952, "name": {"id": 9837, "ja_JP": "\u52d5\u7684\u30a8\u30f3\u30b0\u30e9\u30e0\u7d50\u6676\u7247", "zh_CN": "\u53d8\u5316\u7684\u80fd\u91cf\u7ed3\u6676\u7247"}}, {"content_id": "pub0201", "id": 172001400, "drop_rate": 952, "name": {"id": 682, "ja_JP": "\u30eb\u30fc\u30ce\u30b8\u30a7\u30e0\u30fb\u30a4\u30df\u30e5\u30fc", "zh_CN": "\u5362\u8bfa\u5b9d\u77f3\u00b7\u4f0a\u7f2a"}}, {"content_id": "pub0201", "id": 165001200, "drop_rate": 286, "name": {"id": 8135, "ja_JP": "\u571f\u7cbe\u306e\u7d50\u6676\u7247G1", "zh_CN": "\u571f\u7cbe\u7684\u7ed3\u6676\u7247G1"}}, {"content_id": "pub0201", "id": 502018008, "drop_rate": 7}]}, {"EnemyId": "E300_04_00_03001", "MinLv": 47, "MaxLv": 47, "Name": {"id": 224, "ja_JP": "\u5c71\u8cca\u306e\u8b77\u885b", "zh_CN": "\u5c71\u8d3c\u62a4\u536b"}, "Drops": [{"content_id": "pub0201", "id": 150018000, "drop_rate": 500, "name": {"id": 1018, "ja_JP": "\u5c71\u8cca\u306e\u8b77\u885b\u306e\u4e0a\u7740", "zh_CN": "\u5c71\u8d3c\u62a4\u536b\u7684\u4e0a\u8863"}}, {"content_id": "pub0201", "id": 154000000, "drop_rate": 2000, "name": {"id": 9836, "ja_JP": "\u52d5\u7684\u30a8\u30f3\u30b0\u30e9\u30e0\u306e\u6b20\u7247", "zh_CN": "\u53d8\u5316\u7684\u80fd\u91cf\u788e\u7247"}}, {"content_id": "pub0201", "id": 154100000, "drop_rate": 1333, "name": {"id": 9837, "ja_JP": "\u52d5\u7684\u30a8\u30f3\u30b0\u30e9\u30e0\u7d50\u6676\u7247", "zh_CN": "\u53d8\u5316\u7684\u80fd\u91cf\u7ed3\u6676\u7247"}}, {"content_id": "pub0201", "id": 172001400, "drop_rate": 1333, "name": {"id": 682, "ja_JP": "\u30eb\u30fc\u30ce\u30b8\u30a7\u30e0\u30fb\u30a4\u30df\u30e5\u30fc", "zh_CN": "\u5362\u8bfa\u5b9d\u77f3\u00b7\u4f0a\u7f2a"}}, {"content_id": "pub0201", "id": 165001200, "drop_rate": 400, "name": {"id": 8135, "ja_JP": "\u571f\u7cbe\u306e\u7d50\u6676\u7247G1", "zh_CN": "\u571f\u7cbe\u7684\u7ed3\u6676\u7247G1"}}, {"content_id": "pub0201", "id": 502018011, "drop_rate": 9}]}, {"EnemyId": "E300_03_00_03001", "MinLv": 47, "MaxLv": 47, "Name": {"id": 66, "ja_JP": "\u5c71\u8cca\u306e\u8853\u58eb", "zh_CN": "\u5c71\u8d3c\u672f\u58eb"}, "Drops": [{"content_id": "pub0201", "id": 154000000, "drop_rate": 2727, "name": {"id": 9836, "ja_JP": "\u52d5\u7684\u30a8\u30f3\u30b0\u30e9\u30e0\u306e\u6b20\u7247", "zh_CN": "\u53d8\u5316\u7684\u80fd\u91cf\u788e\u7247"}}, {"content_id": "pub0201", "id": 154100000, "drop_rate": 1818, "name": {"id": 9837, "ja_JP": "\u52d5\u7684\u30a8\u30f3\u30b0\u30e9\u30e0\u7d50\u6676\u7247", "zh_CN": "\u53d8\u5316\u7684\u80fd\u91cf\u7ed3\u6676\u7247"}}, {"content_id": "pub0201", "id": 172001400, "drop_rate": 1818, "name": {"id": 682, "ja_JP": "\u30eb\u30fc\u30ce\u30b8\u30a7\u30e0\u30fb\u30a4\u30df\u30e5\u30fc", "zh_CN": "\u5362\u8bfa\u5b9d\u77f3\u00b7\u4f0a\u7f2a"}}, {"content_id": "pub0201", "id": 165001200, "drop_rate": 545, "name": {"id": 8135, "ja_JP": "\u571f\u7cbe\u306e\u7d50\u6676\u7247G1", "zh_CN": "\u571f\u7cbe\u7684\u7ed3\u6676\u7247G1"}}, {"content_id": "pub0201", "id": 502018004, "drop_rate": 13}]}]}}, {"HabitatId": "ES_pub0201_Area_1", "HabitatTag": "ES_pub0201_Area_1_a", "HabitatKey": "pub0201_EN_ES_pub0201_Area_1_a", "RelativeLocation": {"X": 5550.0, "Y": 3620.0, "Z": 1630.0}, "Data": {"id": "ES_pub0201_Area_1", "members": [{"EnemyId": "E300_00_00_03001", "MinLv": 44, "MaxLv": 44, "Name": {"id": 63, "ja_JP": "\u5c71\u8cca", "zh_CN": "\u5c71\u8d3c"}, "Drops": [{"content_id": "pub0201", "id": 154000000, "drop_rate": 2000, "name": {"id": 9836, "ja_JP": "\u52d5\u7684\u30a8\u30f3\u30b0\u30e9\u30e0\u306e\u6b20\u7247", "zh_CN": "\u53d8\u5316\u7684\u80fd\u91cf\u788e\u7247"}}, {"content_id": "pub0201", "id": 154100000, "drop_rate": 1333, "name": {"id": 9837, "ja_JP": "\u52d5\u7684\u30a8\u30f3\u30b0\u30e9\u30e0\u7d50\u6676\u7247", "zh_CN": "\u53d8\u5316\u7684\u80fd\u91cf\u7ed3\u6676\u7247"}}, {"content_id": "pub0201", "id": 172001400, "drop_rate": 1333, "name": {"id": 682, "ja_JP": "\u30eb\u30fc\u30ce\u30b8\u30a7\u30e0\u30fb\u30a4\u30df\u30e5\u30fc", "zh_CN": "\u5362\u8bfa\u5b9d\u77f3\u00b7\u4f0a\u7f2a"}}, {"content_id": "pub0201", "id": 165001200, "drop_rate": 400, "name": {"id": 8135, "ja_JP": "\u571f\u7cbe\u306e\u7d50\u6676\u7247G1", "zh_CN": "\u571f\u7cbe\u7684\u7ed3\u6676\u7247G1"}}, {"content_id": "pub0201", "id": 502018001, "drop_rate": 9}]}, {"EnemyId": "E007_00_02_03001", "MinLv": 44, "MaxLv": 44, "Name": {"id": 253, "ja_JP": "\u30ed\u30c3\u30af\u30ea\u30b6\u30fc\u30c9", "zh_CN": "\u5ca9\u8725\u8734"}, "Drops": [{"content_id": "pub0201", "id": 154000000, "drop_rate": 3000, "name": {"id": 9836, "ja_JP": "\u52d5\u7684\u30a8\u30f3\u30b0\u30e9\u30e0\u306e\u6b20\u7247", "zh_CN": "\u53d8\u5316\u7684\u80fd\u91cf\u788e\u7247"}}, {"content_id": "pub0201", "id": 154100000, "drop_rate": 2000, "name": {"id": 9837, "ja_JP": "\u52d5\u7684\u30a8\u30f3\u30b0\u30e9\u30e0\u7d50\u6676\u7247", "zh_CN": "\u53d8\u5316\u7684\u80fd\u91cf\u7ed3\u6676\u7247"}}, {"content_id": "pub0201", "id": 172001400, "drop_rate": 2000, "name": {"id": 682, "ja_JP": "\u30eb\u30fc\u30ce\u30b8\u30a7\u30e0\u30fb\u30a4\u30df\u30e5\u30fc", "zh_CN": "\u5362\u8bfa\u5b9d\u77f3\u00b7\u4f0a\u7f2a"}}, {"content_id": "pub0201", "id": 165001200, "drop_rate": 600, "name": {"id": 8135, "ja_JP": "\u571f\u7cbe\u306e\u7d50\u6676\u7247G1", "zh_CN": "\u571f\u7cbe\u7684\u7ed3\u6676\u7247G1"}}, {"content_id": "pub0201", "id": 502018005, "drop_rate": 14}]}, {"EnemyId": "E020_00_00_03001", "MinLv": 44, "MaxLv": 44, "Name": {"id": 124, "ja_JP": "\u30ab\u30ac\u30c1\u30e4\u30f3\u30de", "zh_CN": "\u9b3c\u706f\u873b\u8713"}, "Drops": [{"content_id": "pub0201", "id": 154000000, "drop_rate": 1666, "name": {"id": 9836, "ja_JP": "\u52d5\u7684\u30a8\u30f3\u30b0\u30e9\u30e0\u306e\u6b20\u7247", "zh_CN": "\u53d8\u5316\u7684\u80fd\u91cf\u788e\u7247"}}, {"content_id": "pub0201", "id": 154100000, "drop_rate": 1111, "name": {"id": 9837, "ja_JP": "\u52d5\u7684\u30a8\u30f3\u30b0\u30e9\u30e0\u7d50\u6676\u7247", "zh_CN": "\u53d8\u5316\u7684\u80fd\u91cf\u7ed3\u6676\u7247"}}, {"content_id": "pub0201", "id": 172001400, "drop_rate": 1111, "name": {"id": 682, "ja_JP": "\u30eb\u30fc\u30ce\u30b8\u30a7\u30e0\u30fb\u30a4\u30df\u30e5\u30fc", "zh_CN": "\u5362\u8bfa\u5b9d\u77f3\u00b7\u4f0a\u7f2a"}}, {"content_id": "pub0201", "id": 165001100, "drop_rate": 333, "name": {"id": 8134, "ja_JP": "\u96f7\u7cbe\u306e\u7d50\u6676\u7247G1", "zh_CN": "\u96f7\u7cbe\u7684\u7ed3\u6676\u7247G1"}}, {"content_id": "pub0201", "id": 502018007, "drop_rate": 8}]}]}}, {"HabitatId": "ES_pub0201_Area_1", "HabitatTag": "ES_pub0201_Area_1_b", "HabitatKey": "pub0201_EN_ES_pub0201_Area_1_b", "RelativeLocation": {"X": 13190.0, "Y": 1880.0, "Z": 2920.0}, "Data": {"id": "ES_pub0201_Area_1", "members": [{"EnemyId": "E300_00_00_03001", "MinLv": 44, "MaxLv": 44, "Name": {"id": 63, "ja_JP": "\u5c71\u8cca", "zh_CN": "\u5c71\u8d3c"}, "Drops": [{"content_id": "pub0201", "id": 154000000, "drop_rate": 2000, "name": {"id": 9836, "ja_JP": "\u52d5\u7684\u30a8\u30f3\u30b0\u30e9\u30e0\u306e\u6b20\u7247", "zh_CN": "\u53d8\u5316\u7684\u80fd\u91cf\u788e\u7247"}}, {"content_id": "pub0201", "id": 154100000, "drop_rate": 1333, "name": {"id": 9837, "ja_JP": "\u52d5\u7684\u30a8\u30f3\u30b0\u30e9\u30e0\u7d50\u6676\u7247", "zh_CN": "\u53d8\u5316\u7684\u80fd\u91cf\u7ed3\u6676\u7247"}}, {"content_id": "pub0201", "id": 172001400, "drop_rate": 1333, "name": {"id": 682, "ja_JP": "\u30eb\u30fc\u30ce\u30b8\u30a7\u30e0\u30fb\u30a4\u30df\u30e5\u30fc", "zh_CN": "\u5362\u8bfa\u5b9d\u77f3\u00b7\u4f0a\u7f2a"}}, {"content_id": "pub0201", "id": 165001200, "drop_rate": 400, "name": {"id": 8135, "ja_JP": "\u571f\u7cbe\u306e\u7d50\u6676\u7247G1", "zh_CN": "\u571f\u7cbe\u7684\u7ed3\u6676\u7247G1"}}, {"content_id": "pub0201", "id": 502018001, "drop_rate": 9}]}, {"EnemyId": "E007_00_02_03001", "MinLv": 44, "MaxLv": 44, "Name": {"id": 253, "ja_JP": "\u30ed\u30c3\u30af\u30ea\u30b6\u30fc\u30c9", "zh_CN": "\u5ca9\u8725\u8734"}, "Drops": [{"content_id": "pub0201", "id": 154000000, "drop_rate": 3000, "name": {"id": 9836, "ja_JP": "\u52d5\u7684\u30a8\u30f3\u30b0\u30e9\u30e0\u306e\u6b20\u7247", "zh_CN": "\u53d8\u5316\u7684\u80fd\u91cf\u788e\u7247"}}, {"content_id": "pub0201", "id": 154100000, "drop_rate": 2000, "name": {"id": 9837, "ja_JP": "\u52d5\u7684\u30a8\u30f3\u30b0\u30e9\u30e0\u7d50\u6676\u7247", "zh_CN": "\u53d8\u5316\u7684\u80fd\u91cf\u7ed3\u6676\u7247"}}, {"content_id": "pub0201", "id": 172001400, "drop_rate": 2000, "name": {"id": 682, "ja_JP": "\u30eb\u30fc\u30ce\u30b8\u30a7\u30e0\u30fb\u30a4\u30df\u30e5\u30fc", "zh_CN": "\u5362\u8bfa\u5b9d\u77f3\u00b7\u4f0a\u7f2a"}}, {"content_id": "pub0201", "id": 165001200, "drop_rate": 600, "name": {"id": 8135, "ja_JP": "\u571f\u7cbe\u306e\u7d50\u6676\u7247G1", "zh_CN": "\u571f\u7cbe\u7684\u7ed3\u6676\u7247G1"}}, {"content_id": "pub0201", "id": 502018005, "drop_rate": 14}]}, {"EnemyId": "E020_00_00_03001", "MinLv": 44, "MaxLv": 44, "Name": {"id": 124, "ja_JP": "\u30ab\u30ac\u30c1\u30e4\u30f3\u30de", "zh_CN": "\u9b3c\u706f\u873b\u8713"}, "Drops": [{"content_id": "pub0201", "id": 154000000, "drop_rate": 1666, "name": {"id": 9836, "ja_JP": "\u52d5\u7684\u30a8\u30f3\u30b0\u30e9\u30e0\u306e\u6b20\u7247", "zh_CN": "\u53d8\u5316\u7684\u80fd\u91cf\u788e\u7247"}}, {"content_id": "pub0201", "id": 154100000, "drop_rate": 1111, "name": {"id": 9837, "ja_JP": "\u52d5\u7684\u30a8\u30f3\u30b0\u30e9\u30e0\u7d50\u6676\u7247", "zh_CN": "\u53d8\u5316\u7684\u80fd\u91cf\u7ed3\u6676\u7247"}}, {"content_id": "pub0201", "id": 172001400, "drop_rate": 1111, "name": {"id": 682, "ja_JP": "\u30eb\u30fc\u30ce\u30b8\u30a7\u30e0\u30fb\u30a4\u30df\u30e5\u30fc", "zh_CN": "\u5362\u8bfa\u5b9d\u77f3\u00b7\u4f0a\u7f2a"}}, {"content_id": "pub0201", "id": 165001100, "drop_rate": 333, "name": {"id": 8134, "ja_JP": "\u96f7\u7cbe\u306e\u7d50\u6676\u7247G1", "zh_CN": "\u96f7\u7cbe\u7684\u7ed3\u6676\u7247G1"}}, {"content_id": "pub0201", "id": 502018007, "drop_rate": 8}]}]}}, {"HabitatId": "ES_pub0201_Area_2", "HabitatTag": "ES_pub0201_Area_2", "HabitatKey": "pub0201_EN_ES_pub0201_Area_2", "RelativeLocation": {"X": 6440.0, "Y": 11170.0, "Z": 520.0}, "Data": {"id": "ES_pub0201_Area_2", "members": [{"EnemyId": "E300_00_00_03001", "MinLv": 45, "MaxLv": 46, "Name": {"id": 63, "ja_JP": "\u5c71\u8cca", "zh_CN": "\u5c71\u8d3c"}, "Drops": [{"content_id": "pub0201", "id": 154000000, "drop_rate": 2000, "name": {"id": 9836, "ja_JP": "\u52d5\u7684\u30a8\u30f3\u30b0\u30e9\u30e0\u306e\u6b20\u7247", "zh_CN": "\u53d8\u5316\u7684\u80fd\u91cf\u788e\u7247"}}, {"content_id": "pub0201", "id": 154100000, "drop_rate": 1333, "name": {"id": 9837, "ja_JP": "\u52d5\u7684\u30a8\u30f3\u30b0\u30e9\u30e0\u7d50\u6676\u7247", "zh_CN": "\u53d8\u5316\u7684\u80fd\u91cf\u7ed3\u6676\u7247"}}, {"content_id": "pub0201", "id": 172001400, "drop_rate": 1333, "name": {"id": 682, "ja_JP": "\u30eb\u30fc\u30ce\u30b8\u30a7\u30e0\u30fb\u30a4\u30df\u30e5\u30fc", "zh_CN": "\u5362\u8bfa\u5b9d\u77f3\u00b7\u4f0a\u7f2a"}}, {"content_id": "pub0201", "id": 165001200, "drop_rate": 400, "name": {"id": 8135, "ja_JP": "\u571f\u7cbe\u306e\u7d50\u6676\u7247G1", "zh_CN": "\u571f\u7cbe\u7684\u7ed3\u6676\u7247G1"}}, {"content_id": "pub0201", "id": 502018001, "drop_rate": 9}]}, {"EnemyId": "E300_02_00_03001", "MinLv": 45, "MaxLv": 46, "Name": {"id": 65, "ja_JP": "\u5c71\u8cca\u306e\u65a5\u5019", "zh_CN": "\u5c71\u8d3c\u65a5\u5019"}, "Drops": [{"content_id": "pub0201", "id": 150009700, "drop_rate": 500, "name": {"id": 471, "ja_JP": "\u5c71\u8cca\u306e\u65a5\u5019\u306e\u6226\u9774", "zh_CN": "\u5c71\u8d3c\u65a5\u5019\u7684\u6218\u9774"}}, {"content_id": "pub0201", "id": 154000000, "drop_rate": 1500, "name": {"id": 9836, "ja_JP": "\u52d5\u7684\u30a8\u30f3\u30b0\u30e9\u30e0\u306e\u6b20\u7247", "zh_CN": "\u53d8\u5316\u7684\u80fd\u91cf\u788e\u7247"}}, {"content_id": "pub0201", "id": 154100000, "drop_rate": 1000, "name": {"id": 9837, "ja_JP": "\u52d5\u7684\u30a8\u30f3\u30b0\u30e9\u30e0\u7d50\u6676\u7247", "zh_CN": "\u53d8\u5316\u7684\u80fd\u91cf\u7ed3\u6676\u7247"}}, {"content_id": "pub0201", "id": 172001400, "drop_rate": 1000, "name": {"id": 682, "ja_JP": "\u30eb\u30fc\u30ce\u30b8\u30a7\u30e0\u30fb\u30a4\u30df\u30e5\u30fc", "zh_CN": "\u5362\u8bfa\u5b9d\u77f3\u00b7\u4f0a\u7f2a"}}, {"content_id": "pub0201", "id": 165001200, "drop_rate": 300, "name": {"id": 8135, "ja_JP": "\u571f\u7cbe\u306e\u7d50\u6676\u7247G1", "zh_CN": "\u571f\u7cbe\u7684\u7ed3\u6676\u7247G1"}}, {"content_id": "pub0201", "id": 502018003, "drop_rate": 7}]}, {"EnemyId": "E300_03_00_03001", "MinLv": 45, "MaxLv": 46, "Name": {"id": 66, "ja_JP": "\u5c71\u8cca\u306e\u8853\u58eb", "zh_CN": "\u5c71\u8d3c\u672f\u58eb"}, "Drops": [{"content_id": "pub0201", "id": 154000000, "drop_rate": 2727, "name": {"id": 9836, "ja_JP": "\u52d5\u7684\u30a8\u30f3\u30b0\u30e9\u30e0\u306e\u6b20\u7247", "zh_CN": "\u53d8\u5316\u7684\u80fd\u91cf\u788e\u7247"}}, {"content_id": "pub0201", "id": 154100000, "drop_rate": 1818, "name": {"id": 9837, "ja_JP": "\u52d5\u7684\u30a8\u30f3\u30b0\u30e9\u30e0\u7d50\u6676\u7247", "zh_CN": "\u53d8\u5316\u7684\u80fd\u91cf\u7ed3\u6676\u7247"}}, {"content_id": "pub0201", "id": 172001400, "drop_rate": 1818, "name": {"id": 682, "ja_JP": "\u30eb\u30fc\u30ce\u30b8\u30a7\u30e0\u30fb\u30a4\u30df\u30e5\u30fc", "zh_CN": "\u5362\u8bfa\u5b9d\u77f3\u00b7\u4f0a\u7f2a"}}, {"content_id": "pub0201", "id": 165001200, "drop_rate": 545, "name": {"id": 8135, "ja_JP": "\u571f\u7cbe\u306e\u7d50\u6676\u7247G1", "zh_CN": "\u571f\u7cbe\u7684\u7ed3\u6676\u7247G1"}}, {"content_id": "pub0201", "id": 502018004, "drop_rate": 13}]}]}}, {"HabitatId": "ES_pub0201_Area_3", "HabitatTag": "ES_pub0201_Area_3_a", "HabitatKey": "pub0201_EN_ES_pub0201_Area_3_a", "RelativeLocation": {"X": 12620.0, "Y": 11670.0, "Z": -80.0}, "Data": {"id": "ES_pub0201_Area_3", "members": [{"EnemyId": "E300_01_00_03001", "MinLv": 45, "MaxLv": 46, "Name": {"id": 64, "ja_JP": "\u5c71\u8cca\u306e\u5c04\u624b", "zh_CN": "\u5c71\u8d3c\u5c04\u624b"}, "Drops": [{"content_id": "pub0201", "id": 154000000, "drop_rate": 1200, "name": {"id": 9836, "ja_JP": "\u52d5\u7684\u30a8\u30f3\u30b0\u30e9\u30e0\u306e\u6b20\u7247", "zh_CN": "\u53d8\u5316\u7684\u80fd\u91cf\u788e\u7247"}}, {"content_id": "pub0201", "id": 154100000, "drop_rate": 800, "name": {"id": 9837, "ja_JP": "\u52d5\u7684\u30a8\u30f3\u30b0\u30e9\u30e0\u7d50\u6676\u7247", "zh_CN": "\u53d8\u5316\u7684\u80fd\u91cf\u7ed3\u6676\u7247"}}, {"content_id": "pub0201", "id": 172001400, "drop_rate": 800, "name": {"id": 682, "ja_JP": "\u30eb\u30fc\u30ce\u30b8\u30a7\u30e0\u30fb\u30a4\u30df\u30e5\u30fc", "zh_CN": "\u5362\u8bfa\u5b9d\u77f3\u00b7\u4f0a\u7f2a"}}, {"content_id": "pub0201", "id": 165001200, "drop_rate": 240, "name": {"id": 8135, "ja_JP": "\u571f\u7cbe\u306e\u7d50\u6676\u7247G1", "zh_CN": "\u571f\u7cbe\u7684\u7ed3\u6676\u7247G1"}}, {"content_id": "pub0201", "id": 502018002, "drop_rate": 6}]}, {"EnemyId": "E300_02_00_03001", "MinLv": 45, "MaxLv": 46, "Name": {"id": 65, "ja_JP": "\u5c71\u8cca\u306e\u65a5\u5019", "zh_CN": "\u5c71\u8d3c\u65a5\u5019"}, "Drops": [{"content_id": "pub0201", "id": 150009700, "drop_rate": 500, "name": {"id": 471, "ja_JP": "\u5c71\u8cca\u306e\u65a5\u5019\u306e\u6226\u9774", "zh_CN": "\u5c71\u8d3c\u65a5\u5019\u7684\u6218\u9774"}}, {"content_id": "pub0201", "id": 154000000, "drop_rate": 1500, "name": {"id": 9836, "ja_JP": "\u52d5\u7684\u30a8\u30f3\u30b0\u30e9\u30e0\u306e\u6b20\u7247", "zh_CN": "\u53d8\u5316\u7684\u80fd\u91cf\u788e\u7247"}}, {"content_id": "pub0201", "id": 154100000, "drop_rate": 1000, "name": {"id": 9837, "ja_JP": "\u52d5\u7684\u30a8\u30f3\u30b0\u30e9\u30e0\u7d50\u6676\u7247", "zh_CN": "\u53d8\u5316\u7684\u80fd\u91cf\u7ed3\u6676\u7247"}}, {"content_id": "pub0201", "id": 172001400, "drop_rate": 1000, "name": {"id": 682, "ja_JP": "\u30eb\u30fc\u30ce\u30b8\u30a7\u30e0\u30fb\u30a4\u30df\u30e5\u30fc", "zh_CN": "\u5362\u8bfa\u5b9d\u77f3\u00b7\u4f0a\u7f2a"}}, {"content_id": "pub0201", "id": 165001200, "drop_rate": 300, "name": {"id": 8135, "ja_JP": "\u571f\u7cbe\u306e\u7d50\u6676\u7247G1", "zh_CN": "\u571f\u7cbe\u7684\u7ed3\u6676\u7247G1"}}, {"content_id": "pub0201", "id": 502018003, "drop_rate": 7}]}]}}, {"HabitatId": "ES_pub0201_Area_3", "HabitatTag": "ES_pub0201_Area_3_b", "HabitatKey": "pub0201_EN_ES_pub0201_Area_3_b", "RelativeLocation": {"X": 19210.0, "Y": 6740.0, "Z": -510.0}, "Data": {"id": "ES_pub0201_Area_3", "members": [{"EnemyId": "E300_01_00_03001", "MinLv": 45, "MaxLv": 46, "Name": {"id": 64, "ja_JP": "\u5c71\u8cca\u306e\u5c04\u624b", "zh_CN": "\u5c71\u8d3c\u5c04\u624b"}, "Drops": [{"content_id": "pub0201", "id": 154000000, "drop_rate": 1200, "name": {"id": 9836, "ja_JP": "\u52d5\u7684\u30a8\u30f3\u30b0\u30e9\u30e0\u306e\u6b20\u7247", "zh_CN": "\u53d8\u5316\u7684\u80fd\u91cf\u788e\u7247"}}, {"content_id": "pub0201", "id": 154100000, "drop_rate": 800, "name": {"id": 9837, "ja_JP": "\u52d5\u7684\u30a8\u30f3\u30b0\u30e9\u30e0\u7d50\u6676\u7247", "zh_CN": "\u53d8\u5316\u7684\u80fd\u91cf\u7ed3\u6676\u7247"}}, {"content_id": "pub0201", "id": 172001400, "drop_rate": 800, "name": {"id": 682, "ja_JP": "\u30eb\u30fc\u30ce\u30b8\u30a7\u30e0\u30fb\u30a4\u30df\u30e5\u30fc", "zh_CN": "\u5362\u8bfa\u5b9d\u77f3\u00b7\u4f0a\u7f2a"}}, {"content_id": "pub0201", "id": 165001200, "drop_rate": 240, "name": {"id": 8135, "ja_JP": "\u571f\u7cbe\u306e\u7d50\u6676\u7247G1", "zh_CN": "\u571f\u7cbe\u7684\u7ed3\u6676\u7247G1"}}, {"content_id": "pub0201", "id": 502018002, "drop_rate": 6}]}, {"EnemyId": "E300_02_00_03001", "MinLv": 45, "MaxLv": 46, "Name": {"id": 65, "ja_JP": "\u5c71\u8cca\u306e\u65a5\u5019", "zh_CN": "\u5c71\u8d3c\u65a5\u5019"}, "Drops": [{"content_id": "pub0201", "id": 150009700, "drop_rate": 500, "name": {"id": 471, "ja_JP": "\u5c71\u8cca\u306e\u65a5\u5019\u306e\u6226\u9774", "zh_CN": "\u5c71\u8d3c\u65a5\u5019\u7684\u6218\u9774"}}, {"content_id": "pub0201", "id": 154000000, "drop_rate": 1500, "name": {"id": 9836, "ja_JP": "\u52d5\u7684\u30a8\u30f3\u30b0\u30e9\u30e0\u306e\u6b20\u7247", "zh_CN": "\u53d8\u5316\u7684\u80fd\u91cf\u788e\u7247"}}, {"content_id": "pub0201", "id": 154100000, "drop_rate": 1000, "name": {"id": 9837, "ja_JP": "\u52d5\u7684\u30a8\u30f3\u30b0\u30e9\u30e0\u7d50\u6676\u7247", "zh_CN": "\u53d8\u5316\u7684\u80fd\u91cf\u7ed3\u6676\u7247"}}, {"content_id": "pub0201", "id": 172001400, "drop_rate": 1000, "name": {"id": 682, "ja_JP": "\u30eb\u30fc\u30ce\u30b8\u30a7\u30e0\u30fb\u30a4\u30df\u30e5\u30fc", "zh_CN": "\u5362\u8bfa\u5b9d\u77f3\u00b7\u4f0a\u7f2a"}}, {"content_id": "pub0201", "id": 165001200, "drop_rate": 300, "name": {"id": 8135, "ja_JP": "\u571f\u7cbe\u306e\u7d50\u6676\u7247G1", "zh_CN": "\u571f\u7cbe\u7684\u7ed3\u6676\u7247G1"}}, {"content_id": "pub0201", "id": 502018003, "drop_rate": 7}]}]}}, {"HabitatId": "ES_pub0201_Area_4", "HabitatTag": "ES_pub0201_Area_4_a", "HabitatKey": "pub0201_EN_ES_pub0201_Area_4_a", "RelativeLocation": {"X": 24070.0, "Y": 1580.0, "Z": 510.0}, "Data": {"id": "ES_pub0201_Area_4", "members": [{"EnemyId": "E027_03_00_03001", "MinLv": 47, "MaxLv": 47, "Name": {"id": 271, "ja_JP": "\u30a2\u30fc\u30b9\u30a8\u30ec\u30e1\u30f3\u30c8", "zh_CN": "\u5730\u5143\u7d20\u7cbe\u7075"}, "Drops": [{"content_id": "pub0201", "id": 154000000, "drop_rate": 1428, "name": {"id": 9836, "ja_JP": "\u52d5\u7684\u30a8\u30f3\u30b0\u30e9\u30e0\u306e\u6b20\u7247", "zh_CN": "\u53d8\u5316\u7684\u80fd\u91cf\u788e\u7247"}}, {"content_id": "pub0201", "id": 154100000, "drop_rate": 952, "name": {"id": 9837, "ja_JP": "\u52d5\u7684\u30a8\u30f3\u30b0\u30e9\u30e0\u7d50\u6676\u7247", "zh_CN": "\u53d8\u5316\u7684\u80fd\u91cf\u7ed3\u6676\u7247"}}, {"content_id": "pub0201", "id": 172001400, "drop_rate": 952, "name": {"id": 682, "ja_JP": "\u30eb\u30fc\u30ce\u30b8\u30a7\u30e0\u30fb\u30a4\u30df\u30e5\u30fc", "zh_CN": "\u5362\u8bfa\u5b9d\u77f3\u00b7\u4f0a\u7f2a"}}, {"content_id": "pub0201", "id": 165001200, "drop_rate": 286, "name": {"id": 8135, "ja_JP": "\u571f\u7cbe\u306e\u7d50\u6676\u7247G1", "zh_CN": "\u571f\u7cbe\u7684\u7ed3\u6676\u7247G1"}}, {"content_id": "pub0201", "id": 502018008, "drop_rate": 7}]}, {"EnemyId": "E015_02_00_03001", "MinLv": 47, "MaxLv": 47, "Name": {"id": 56, "ja_JP": "\u30d6\u30e9\u30b9\u30c8\u30df\u30fc\u30f3", "zh_CN": "\u7206\u708e\u8702"}, "Drops": [{"content_id": "pub0201", "id": 154000000, "drop_rate": 1875, "name": {"id": 9836, "ja_JP": "\u52d5\u7684\u30a8\u30f3\u30b0\u30e9\u30e0\u306e\u6b20\u7247", "zh_CN": "\u53d8\u5316\u7684\u80fd\u91cf\u788e\u7247"}}, {"content_id": "pub0201", "id": 154100000, "drop_rate": 1250, "name": {"id": 9837, "ja_JP": "\u52d5\u7684\u30a8\u30f3\u30b0\u30e9\u30e0\u7d50\u6676\u7247", "zh_CN": "\u53d8\u5316\u7684\u80fd\u91cf\u7ed3\u6676\u7247"}}, {"content_id": "pub0201", "id": 172001400, "drop_rate": 1250, "name": {"id": 682, "ja_JP": "\u30eb\u30fc\u30ce\u30b8\u30a7\u30e0\u30fb\u30a4\u30df\u30e5\u30fc", "zh_CN": "\u5362\u8bfa\u5b9d\u77f3\u00b7\u4f0a\u7f2a"}}, {"content_id": "pub0201", "id": 165000900, "drop_rate": 375, "name": {"id": 8132, "ja_JP": "\u706b\u7cbe\u306e\u7d50\u6676\u7247G1", "zh_CN": "\u706b\u7cbe\u7684\u7ed3\u6676\u7247G1"}}, {"content_id": "pub0201", "id": 502018010, "drop_rate": 9}]}, {"EnemyId": "E020_01_00_03001", "MinLv": 47, "MaxLv": 47, "Name": {"id": 216, "ja_JP": "\u30aa\u30aa\u30ab\u30ac\u30c1\u30e4\u30f3\u30de", "zh_CN": "\u5927\u9b3c\u706f\u873b\u8713"}, "Drops": [{"content_id": "pub0201", "id": 154000000, "drop_rate": 2000, "name": {"id": 9836, "ja_JP": "\u52d5\u7684\u30a8\u30f3\u30b0\u30e9\u30e0\u306e\u6b20\u7247", "zh_CN": "\u53d8\u5316\u7684\u80fd\u91cf\u788e\u7247"}}, {"content_id": "pub0201", "id": 154100000, "drop_rate": 1333, "name": {"id": 9837, "ja_JP": "\u52d5\u7684\u30a8\u30f3\u30b0\u30e9\u30e0\u7d50\u6676\u7247", "zh_CN": "\u53d8\u5316\u7684\u80fd\u91cf\u7ed3\u6676\u7247"}}, {"content_id": "pub0201", "id": 172001400, "drop_rate": 1333, "name": {"id": 682, "ja_JP": "\u30eb\u30fc\u30ce\u30b8\u30a7\u30e0\u30fb\u30a4\u30df\u30e5\u30fc", "zh_CN": "\u5362\u8bfa\u5b9d\u77f3\u00b7\u4f0a\u7f2a"}}, {"content_id": "pub0201", "id": 165001100, "drop_rate": 400, "name": {"id": 8134, "ja_JP": "\u96f7\u7cbe\u306e\u7d50\u6676\u7247G1", "zh_CN": "\u96f7\u7cbe\u7684\u7ed3\u6676\u7247G1"}}, {"content_id": "pub0201", "id": 502018012, "drop_rate": 9}]}]}}, {"HabitatId": "ES_pub0201_Area_4", "HabitatTag": "ES_pub0201_Area_4_b", "HabitatKey": "pub0201_EN_ES_pub0201_Area_4_b", "RelativeLocation": {"X": 22090.0, "Y": 1510.0, "Z": 1890.0}, "Data": {"id": "ES_pub0201_Area_4", "members": [{"EnemyId": "E027_03_00_03001", "MinLv": 47, "MaxLv": 47, "Name": {"id": 271, "ja_JP": "\u30a2\u30fc\u30b9\u30a8\u30ec\u30e1\u30f3\u30c8", "zh_CN": "\u5730\u5143\u7d20\u7cbe\u7075"}, "Drops": [{"content_id": "pub0201", "id": 154000000, "drop_rate": 1428, "name": {"id": 9836, "ja_JP": "\u52d5\u7684\u30a8\u30f3\u30b0\u30e9\u30e0\u306e\u6b20\u7247", "zh_CN": "\u53d8\u5316\u7684\u80fd\u91cf\u788e\u7247"}}, {"content_id": "pub0201", "id": 154100000, "drop_rate": 952, "name": {"id": 9837, "ja_JP": "\u52d5\u7684\u30a8\u30f3\u30b0\u30e9\u30e0\u7d50\u6676\u7247", "zh_CN": "\u53d8\u5316\u7684\u80fd\u91cf\u7ed3\u6676\u7247"}}, {"content_id": "pub0201", "id": 172001400, "drop_rate": 952, "name": {"id": 682, "ja_JP": "\u30eb\u30fc\u30ce\u30b8\u30a7\u30e0\u30fb\u30a4\u30df\u30e5\u30fc", "zh_CN": "\u5362\u8bfa\u5b9d\u77f3\u00b7\u4f0a\u7f2a"}}, {"content_id": "pub0201", "id": 165001200, "drop_rate": 286, "name": {"id": 8135, "ja_JP": "\u571f\u7cbe\u306e\u7d50\u6676\u7247G1", "zh_CN": "\u571f\u7cbe\u7684\u7ed3\u6676\u7247G1"}}, {"content_id": "pub0201", "id": 502018008, "drop_rate": 7}]}, {"EnemyId": "E015_02_00_03001", "MinLv": 47, "MaxLv": 47, "Name": {"id": 56, "ja_JP": "\u30d6\u30e9\u30b9\u30c8\u30df\u30fc\u30f3", "zh_CN": "\u7206\u708e\u8702"}, "Drops": [{"content_id": "pub0201", "id": 154000000, "drop_rate": 1875, "name": {"id": 9836, "ja_JP": "\u52d5\u7684\u30a8\u30f3\u30b0\u30e9\u30e0\u306e\u6b20\u7247", "zh_CN": "\u53d8\u5316\u7684\u80fd\u91cf\u788e\u7247"}}, {"content_id": "pub0201", "id": 154100000, "drop_rate": 1250, "name": {"id": 9837, "ja_JP": "\u52d5\u7684\u30a8\u30f3\u30b0\u30e9\u30e0\u7d50\u6676\u7247", "zh_CN": "\u53d8\u5316\u7684\u80fd\u91cf\u7ed3\u6676\u7247"}}, {"content_id": "pub0201", "id": 172001400, "drop_rate": 1250, "name": {"id": 682, "ja_JP": "\u30eb\u30fc\u30ce\u30b8\u30a7\u30e0\u30fb\u30a4\u30df\u30e5\u30fc", "zh_CN": "\u5362\u8bfa\u5b9d\u77f3\u00b7\u4f0a\u7f2a"}}, {"content_id": "pub0201", "id": 165000900, "drop_rate": 375, "name": {"id": 8132, "ja_JP": "\u706b\u7cbe\u306e\u7d50\u6676\u7247G1", "zh_CN": "\u706b\u7cbe\u7684\u7ed3\u6676\u7247G1"}}, {"content_id": "pub0201", "id": 502018010, "drop_rate": 9}]}, {"EnemyId": "E020_01_00_03001", "MinLv": 47, "MaxLv": 47, "Name": {"id": 216, "ja_JP": "\u30aa\u30aa\u30ab\u30ac\u30c1\u30e4\u30f3\u30de", "zh_CN": "\u5927\u9b3c\u706f\u873b\u8713"}, "Drops": [{"content_id": "pub0201", "id": 154000000, "drop_rate": 2000, "name": {"id": 9836, "ja_JP": "\u52d5\u7684\u30a8\u30f3\u30b0\u30e9\u30e0\u306e\u6b20\u7247", "zh_CN": "\u53d8\u5316\u7684\u80fd\u91cf\u788e\u7247"}}, {"content_id": "pub0201", "id": 154100000, "drop_rate": 1333, "name": {"id": 9837, "ja_JP": "\u52d5\u7684\u30a8\u30f3\u30b0\u30e9\u30e0\u7d50\u6676\u7247", "zh_CN": "\u53d8\u5316\u7684\u80fd\u91cf\u7ed3\u6676\u7247"}}, {"content_id": "pub0201", "id": 172001400, "drop_rate": 1333, "name": {"id": 682, "ja_JP": "\u30eb\u30fc\u30ce\u30b8\u30a7\u30e0\u30fb\u30a4\u30df\u30e5\u30fc", "zh_CN": "\u5362\u8bfa\u5b9d\u77f3\u00b7\u4f0a\u7f2a"}}, {"content_id": "pub0201", "id": 165001100, "drop_rate": 400, "name": {"id": 8134, "ja_JP": "\u96f7\u7cbe\u306e\u7d50\u6676\u7247G1", "zh_CN": "\u96f7\u7cbe\u7684\u7ed3\u6676\u7247G1"}}, {"content_id": "pub0201", "id": 502018012, "drop_rate": 9}]}]}}]