[{"GatherPointId": 100013101, "GatherPointTag": "A1", "GatherPointKey": "fld001_E_PU_A1", "RelativeLocation": {"X": -33065.0, "Y": -109348.0, "Z": 4489.0}}, {"GatherPointId": 100013101, "GatherPointTag": "A10", "GatherPointKey": "fld001_E_PU_A10", "RelativeLocation": {"X": -54268.0, "Y": -134315.0, "Z": 4488.0}}, {"GatherPointId": 100013101, "GatherPointTag": "A11", "GatherPointKey": "fld001_E_PU_A11", "RelativeLocation": {"X": -56930.0, "Y": -132120.0, "Z": 4490.0}}, {"GatherPointId": 100013101, "GatherPointTag": "A12", "GatherPointKey": "fld001_E_PU_A12", "RelativeLocation": {"X": -53528.0, "Y": -128633.0, "Z": 4488.0}}, {"GatherPointId": 100013101, "GatherPointTag": "A13", "GatherPointKey": "fld001_E_PU_A13", "RelativeLocation": {"X": -42750.0, "Y": -123467.0, "Z": 4489.0}}, {"GatherPointId": 100013101, "GatherPointTag": "A14", "GatherPointKey": "fld001_E_PU_A14", "RelativeLocation": {"X": 31597.0, "Y": -135976.0, "Z": 4669.0}}, {"GatherPointId": 100013101, "GatherPointTag": "A15", "GatherPointKey": "fld001_E_PU_A15", "RelativeLocation": {"X": -11011.0, "Y": -90013.0, "Z": 4391.0}}, {"GatherPointId": 100013101, "GatherPointTag": "A16", "GatherPointKey": "fld001_E_PU_A16", "RelativeLocation": {"X": 28969.0, "Y": -133724.0, "Z": 4669.0}}, {"GatherPointId": 100013101, "GatherPointTag": "A2", "GatherPointKey": "fld001_E_PU_A2", "RelativeLocation": {"X": -14492.0, "Y": -99933.0, "Z": 4481.0}}, {"GatherPointId": 100013101, "GatherPointTag": "A3", "GatherPointKey": "fld001_E_PU_A3", "RelativeLocation": {"X": -11933.0, "Y": -108497.0, "Z": 4489.0}}, {"GatherPointId": 100013101, "GatherPointTag": "A4", "GatherPointKey": "fld001_E_PU_A4", "RelativeLocation": {"X": -8865.0, "Y": -75153.0, "Z": 3813.0}}, {"GatherPointId": 100013101, "GatherPointTag": "A5", "GatherPointKey": "fld001_E_PU_A5", "RelativeLocation": {"X": -7635.0, "Y": -132562.0, "Z": 4489.0}}, {"GatherPointId": 100013101, "GatherPointTag": "A6", "GatherPointKey": "fld001_E_PU_A6", "RelativeLocation": {"X": 20319.0, "Y": -110504.0, "Z": 1778.0}}, {"GatherPointId": 100013101, "GatherPointTag": "A7", "GatherPointKey": "fld001_E_PU_A7", "RelativeLocation": {"X": -43300.0, "Y": -115109.0, "Z": 4489.0}}, {"GatherPointId": 100013101, "GatherPointTag": "A8", "GatherPointKey": "fld001_E_PU_A8", "RelativeLocation": {"X": -44251.0, "Y": -105889.0, "Z": 4489.0}}, {"GatherPointId": 100013101, "GatherPointTag": "A9", "GatherPointKey": "fld001_E_PU_A9", "RelativeLocation": {"X": -6827.0, "Y": -116881.0, "Z": 4489.0}}, {"GatherPointId": 100013102, "GatherPointTag": "A_Fix02", "GatherPointKey": "fld001_E_PU_A_Fix02", "RelativeLocation": {"X": -11856.0, "Y": -84187.0, "Z": 4285.0}}, {"GatherPointId": 100013103, "GatherPointTag": "A_Fix03", "GatherPointKey": "fld001_E_PU_A_Fix03", "RelativeLocation": {"X": -22945.0, "Y": -112154.0, "Z": 4489.0}}, {"GatherPointId": 100013104, "GatherPointTag": "A_Fix04", "GatherPointKey": "fld001_E_PU_A_Fix04", "RelativeLocation": {"X": -7351.0, "Y": -121766.0, "Z": 4489.0}}, {"GatherPointId": 100013105, "GatherPointTag": "A_Fix05", "GatherPointKey": "fld001_E_PU_A_Fix05", "RelativeLocation": {"X": 26158.0, "Y": -100695.0, "Z": 1140.0}}, {"GatherPointId": 100012101, "GatherPointTag": "M1", "GatherPointKey": "fld001_E_PU_M1", "RelativeLocation": {"X": -24058.0, "Y": -70743.0, "Z": 4352.0}}, {"GatherPointId": 100012101, "GatherPointTag": "M10", "GatherPointKey": "fld001_E_PU_M10", "RelativeLocation": {"X": -3668.0, "Y": -117723.0, "Z": 8961.0}}, {"GatherPointId": 100012101, "GatherPointTag": "M11", "GatherPointKey": "fld001_E_PU_M11", "RelativeLocation": {"X": 342.0, "Y": -101023.0, "Z": 6110.0}}, {"GatherPointId": 100012101, "GatherPointTag": "M12", "GatherPointKey": "fld001_E_PU_M12", "RelativeLocation": {"X": 15790.0, "Y": -87890.0, "Z": 1644.0}}, {"GatherPointId": 100012101, "GatherPointTag": "M13", "GatherPointKey": "fld001_E_PU_M13", "RelativeLocation": {"X": -28618.0, "Y": -120003.0, "Z": 6070.0}}, {"GatherPointId": 100012101, "GatherPointTag": "M14", "GatherPointKey": "fld001_E_PU_M14", "RelativeLocation": {"X": -53098.0, "Y": -130853.0, "Z": 4636.0}}, {"GatherPointId": 100012101, "GatherPointTag": "M15", "GatherPointKey": "fld001_E_PU_M15", "RelativeLocation": {"X": 14962.0, "Y": -110173.0, "Z": 2472.0}}, {"GatherPointId": 100012101, "GatherPointTag": "M16", "GatherPointKey": "fld001_E_PU_M16", "RelativeLocation": {"X": 12706.0, "Y": -95141.0, "Z": 5849.0}}, {"GatherPointId": 100012101, "GatherPointTag": "M17", "GatherPointKey": "fld001_E_PU_M17", "RelativeLocation": {"X": -43288.0, "Y": -62996.0, "Z": 2076.0}}, {"GatherPointId": 100012101, "GatherPointTag": "M18", "GatherPointKey": "fld001_E_PU_M18", "RelativeLocation": {"X": -28038.0, "Y": -92023.0, "Z": 5177.0}}, {"GatherPointId": 100012101, "GatherPointTag": "M19", "GatherPointKey": "fld001_E_PU_M19", "RelativeLocation": {"X": -23338.0, "Y": -104413.0, "Z": 5277.0}}, {"GatherPointId": 100012101, "GatherPointTag": "M2", "GatherPointKey": "fld001_E_PU_M2", "RelativeLocation": {"X": -35648.0, "Y": -65173.0, "Z": 2961.0}}, {"GatherPointId": 100012101, "GatherPointTag": "M20", "GatherPointKey": "fld001_E_PU_M20", "RelativeLocation": {"X": 2210.0, "Y": -120370.0, "Z": 9748.0}}, {"GatherPointId": 100012101, "GatherPointTag": "M21", "GatherPointKey": "fld001_E_PU_M21", "RelativeLocation": {"X": -31498.0, "Y": -102783.0, "Z": 6054.0}}, {"GatherPointId": 100012101, "GatherPointTag": "M22", "GatherPointKey": "fld001_E_PU_M22", "RelativeLocation": {"X": -45813.0, "Y": -114395.0, "Z": 4591.0}}, {"GatherPointId": 100012101, "GatherPointTag": "M23", "GatherPointKey": "fld001_E_PU_M23", "RelativeLocation": {"X": -6230.0, "Y": -74060.0, "Z": 4217.0}}, {"GatherPointId": 100012101, "GatherPointTag": "M24", "GatherPointKey": "fld001_E_PU_M24", "RelativeLocation": {"X": 7200.0, "Y": -109000.0, "Z": 7516.0}}, {"GatherPointId": 100012101, "GatherPointTag": "M25", "GatherPointKey": "fld001_E_PU_M25", "RelativeLocation": {"X": 18590.0, "Y": -121050.0, "Z": 10935.0}}, {"GatherPointId": 100012101, "GatherPointTag": "M26", "GatherPointKey": "fld001_E_PU_M26", "RelativeLocation": {"X": -23462.0, "Y": -83510.0, "Z": 4588.0}}, {"GatherPointId": 100012101, "GatherPointTag": "M27", "GatherPointKey": "fld001_E_PU_M27", "RelativeLocation": {"X": -42180.0, "Y": -67610.0, "Z": 6222.0}}, {"GatherPointId": 100012101, "GatherPointTag": "M28", "GatherPointKey": "fld001_E_PU_M28", "RelativeLocation": {"X": -40370.0, "Y": -105070.0, "Z": 4603.0}}, {"GatherPointId": 100012101, "GatherPointTag": "M29", "GatherPointKey": "fld001_E_PU_M29", "RelativeLocation": {"X": -9537.0, "Y": -101060.0, "Z": 6146.0}}, {"GatherPointId": 100012101, "GatherPointTag": "M3", "GatherPointKey": "fld001_E_PU_M3", "RelativeLocation": {"X": 15360.0, "Y": -86624.0, "Z": 4910.0}}, {"GatherPointId": 100012101, "GatherPointTag": "M30", "GatherPointKey": "fld001_E_PU_M30", "RelativeLocation": {"X": -21122.0, "Y": -80685.0, "Z": 5458.0}}, {"GatherPointId": 100012101, "GatherPointTag": "M31", "GatherPointKey": "fld001_E_PU_M31", "RelativeLocation": {"X": -16781.0, "Y": -78674.0, "Z": 6961.0}}, {"GatherPointId": 100012101, "GatherPointTag": "M32", "GatherPointKey": "fld001_E_PU_M32", "RelativeLocation": {"X": -18512.0, "Y": -74904.0, "Z": 6702.0}}, {"GatherPointId": 100012101, "GatherPointTag": "M33", "GatherPointKey": "fld001_E_PU_M33", "RelativeLocation": {"X": -31571.0, "Y": -72460.0, "Z": 3291.0}}, {"GatherPointId": 100012101, "GatherPointTag": "M34", "GatherPointKey": "fld001_E_PU_M34", "RelativeLocation": {"X": -16486.0, "Y": -101593.0, "Z": 5387.0}}, {"GatherPointId": 100012101, "GatherPointTag": "M35", "GatherPointKey": "fld001_E_PU_M35", "RelativeLocation": {"X": 27815.0, "Y": -140791.0, "Z": 4958.0}}, {"GatherPointId": 100012101, "GatherPointTag": "M36", "GatherPointKey": "fld001_E_PU_M36", "RelativeLocation": {"X": -16460.0, "Y": -122261.0, "Z": 5642.0}}, {"GatherPointId": 100012101, "GatherPointTag": "M37", "GatherPointKey": "fld001_E_PU_M37", "RelativeLocation": {"X": -18453.0, "Y": -114522.0, "Z": 5144.0}}, {"GatherPointId": 100012101, "GatherPointTag": "M38", "GatherPointKey": "fld001_E_PU_M38", "RelativeLocation": {"X": -25830.0, "Y": -114991.0, "Z": 5018.0}}, {"GatherPointId": 100012101, "GatherPointTag": "M39", "GatherPointKey": "fld001_E_PU_M39", "RelativeLocation": {"X": -429.0, "Y": -97539.0, "Z": 5759.0}}, {"GatherPointId": 100012101, "GatherPointTag": "M4", "GatherPointKey": "fld001_E_PU_M4", "RelativeLocation": {"X": -41124.0, "Y": -94812.0, "Z": 6027.0}}, {"GatherPointId": 100012101, "GatherPointTag": "M40", "GatherPointKey": "fld001_E_PU_M40", "RelativeLocation": {"X": -20096.0, "Y": -121520.0, "Z": 5751.0}}, {"GatherPointId": 100012101, "GatherPointTag": "M41", "GatherPointKey": "fld001_E_PU_M41", "RelativeLocation": {"X": 23885.0, "Y": -97249.0, "Z": 1130.0}}, {"GatherPointId": 100012101, "GatherPointTag": "M42", "GatherPointKey": "fld001_E_PU_M42", "RelativeLocation": {"X": -10790.0, "Y": -88832.0, "Z": 4791.0}}, {"GatherPointId": 100012101, "GatherPointTag": "M43", "GatherPointKey": "fld001_E_PU_M43", "RelativeLocation": {"X": 15838.0, "Y": -101451.0, "Z": 2008.0}}, {"GatherPointId": 100012101, "GatherPointTag": "M44", "GatherPointKey": "fld001_E_PU_M44", "RelativeLocation": {"X": 12772.0, "Y": -121092.0, "Z": 9985.0}}, {"GatherPointId": 100012101, "GatherPointTag": "M45", "GatherPointKey": "fld001_E_PU_M45", "RelativeLocation": {"X": 12622.0, "Y": -108886.0, "Z": 7893.0}}, {"GatherPointId": 100012101, "GatherPointTag": "M5", "GatherPointKey": "fld001_E_PU_M5", "RelativeLocation": {"X": -18238.0, "Y": -95213.0, "Z": 6541.0}}, {"GatherPointId": 100012101, "GatherPointTag": "M6", "GatherPointKey": "fld001_E_PU_M6", "RelativeLocation": {"X": -7528.0, "Y": -82343.0, "Z": 6573.0}}, {"GatherPointId": 100012101, "GatherPointTag": "M7", "GatherPointKey": "fld001_E_PU_M7", "RelativeLocation": {"X": 1104.0, "Y": -91838.0, "Z": 7736.0}}, {"GatherPointId": 100012101, "GatherPointTag": "M8", "GatherPointKey": "fld001_E_PU_M8", "RelativeLocation": {"X": 13762.0, "Y": -123163.0, "Z": 10927.0}}, {"GatherPointId": 100012101, "GatherPointTag": "M9", "GatherPointKey": "fld001_E_PU_M9", "RelativeLocation": {"X": 30422.0, "Y": -141793.0, "Z": 5254.0}}, {"GatherPointId": 100012102, "GatherPointTag": "M_Fix02", "GatherPointKey": "fld001_E_PU_M_Fix02", "RelativeLocation": {"X": -40338.0, "Y": -71093.0, "Z": 2954.0}}, {"GatherPointId": 100012103, "GatherPointTag": "M_Fix03", "GatherPointKey": "fld001_E_PU_M_Fix03", "RelativeLocation": {"X": 8276.0, "Y": -108020.0, "Z": 7428.0}}, {"GatherPointId": 100012104, "GatherPointTag": "M_Fix04", "GatherPointKey": "fld001_E_PU_M_Fix04", "RelativeLocation": {"X": -42732.0, "Y": -99432.0, "Z": 6017.0}}, {"GatherPointId": 100012105, "GatherPointTag": "M_Fix05", "GatherPointKey": "fld001_E_PU_M_Fix05", "RelativeLocation": {"X": 28632.0, "Y": -137859.0, "Z": 4837.0}}, {"GatherPointId": 100012106, "GatherPointTag": "M_Fix06", "GatherPointKey": "fld001_E_PU_M_Fix06", "RelativeLocation": {"X": -16626.0, "Y": -96826.0, "Z": 5157.0}}, {"GatherPointId": 100011101, "GatherPointTag": "P1", "GatherPointKey": "fld001_E_PU_P1", "RelativeLocation": {"X": -41670.0, "Y": -64889.0, "Z": 2297.0}}, {"GatherPointId": 100011101, "GatherPointTag": "P10", "GatherPointKey": "fld001_E_PU_P10", "RelativeLocation": {"X": 8590.0, "Y": -101430.0, "Z": 6558.0}}, {"GatherPointId": 100011101, "GatherPointTag": "P11", "GatherPointKey": "fld001_E_PU_P11", "RelativeLocation": {"X": -24812.0, "Y": -65211.0, "Z": 5145.0}}, {"GatherPointId": 100011101, "GatherPointTag": "P12", "GatherPointKey": "fld001_E_PU_P12", "RelativeLocation": {"X": -19794.0, "Y": -91863.0, "Z": 6326.0}}, {"GatherPointId": 100011101, "GatherPointTag": "P13", "GatherPointKey": "fld001_E_PU_P13", "RelativeLocation": {"X": -21792.0, "Y": -88569.0, "Z": 4929.0}}, {"GatherPointId": 100011101, "GatherPointTag": "P14", "GatherPointKey": "fld001_E_PU_P14", "RelativeLocation": {"X": 13518.0, "Y": -87005.0, "Z": 1746.0}}, {"GatherPointId": 100011101, "GatherPointTag": "P15", "GatherPointKey": "fld001_E_PU_P15", "RelativeLocation": {"X": 2053.0, "Y": -86867.0, "Z": 5168.0}}, {"GatherPointId": 100011101, "GatherPointTag": "P16", "GatherPointKey": "fld001_E_PU_P16", "RelativeLocation": {"X": -5577.0, "Y": -103327.0, "Z": 5670.0}}, {"GatherPointId": 100011101, "GatherPointTag": "P17", "GatherPointKey": "fld001_E_PU_P17", "RelativeLocation": {"X": 3853.0, "Y": -123087.0, "Z": 10244.0}}, {"GatherPointId": 100011101, "GatherPointTag": "P18", "GatherPointKey": "fld001_E_PU_P18", "RelativeLocation": {"X": 14363.0, "Y": -96477.0, "Z": 6183.0}}, {"GatherPointId": 100011101, "GatherPointTag": "P19", "GatherPointKey": "fld001_E_PU_P19", "RelativeLocation": {"X": -6937.0, "Y": -89077.0, "Z": 5111.0}}, {"GatherPointId": 100011101, "GatherPointTag": "P2", "GatherPointKey": "fld001_E_PU_P2", "RelativeLocation": {"X": -42310.0, "Y": -81150.0, "Z": 5204.0}}, {"GatherPointId": 100011101, "GatherPointTag": "P20", "GatherPointKey": "fld001_E_PU_P20", "RelativeLocation": {"X": 29093.0, "Y": -111607.0, "Z": 11498.0}}, {"GatherPointId": 100011101, "GatherPointTag": "P21", "GatherPointKey": "fld001_E_PU_P21", "RelativeLocation": {"X": -18336.0, "Y": -78967.0, "Z": 6252.0}}, {"GatherPointId": 100011101, "GatherPointTag": "P22", "GatherPointKey": "fld001_E_PU_P22", "RelativeLocation": {"X": -127.0, "Y": -114237.0, "Z": 8283.0}}, {"GatherPointId": 100011101, "GatherPointTag": "P23", "GatherPointKey": "fld001_E_PU_P23", "RelativeLocation": {"X": 2203.0, "Y": -100677.0, "Z": 6626.0}}, {"GatherPointId": 100011101, "GatherPointTag": "P24", "GatherPointKey": "fld001_E_PU_P24", "RelativeLocation": {"X": 15643.0, "Y": -115877.0, "Z": 10082.0}}, {"GatherPointId": 100011101, "GatherPointTag": "P25", "GatherPointKey": "fld001_E_PU_P25", "RelativeLocation": {"X": 17613.0, "Y": -123577.0, "Z": 11620.0}}, {"GatherPointId": 100011101, "GatherPointTag": "P26", "GatherPointKey": "fld001_E_PU_P26", "RelativeLocation": {"X": -33550.0, "Y": -70090.0, "Z": 3436.0}}, {"GatherPointId": 100011101, "GatherPointTag": "P27", "GatherPointKey": "fld001_E_PU_P27", "RelativeLocation": {"X": -43730.0, "Y": -82970.0, "Z": 5262.0}}, {"GatherPointId": 100011101, "GatherPointTag": "P28", "GatherPointKey": "fld001_E_PU_P28", "RelativeLocation": {"X": -30350.0, "Y": -86630.0, "Z": 4918.0}}, {"GatherPointId": 100011101, "GatherPointTag": "P29", "GatherPointKey": "fld001_E_PU_P29", "RelativeLocation": {"X": -1160.0, "Y": -73670.0, "Z": 3846.0}}, {"GatherPointId": 100011101, "GatherPointTag": "P3", "GatherPointKey": "fld001_E_PU_P3", "RelativeLocation": {"X": -40240.0, "Y": -85120.0, "Z": 5321.0}}, {"GatherPointId": 100011101, "GatherPointTag": "P30", "GatherPointKey": "fld001_E_PU_P30", "RelativeLocation": {"X": 27800.0, "Y": -116720.0, "Z": 11587.0}}, {"GatherPointId": 100011101, "GatherPointTag": "P31", "GatherPointKey": "fld001_E_PU_P31", "RelativeLocation": {"X": 10200.0, "Y": -112220.0, "Z": 8355.0}}, {"GatherPointId": 100011101, "GatherPointTag": "P32", "GatherPointKey": "fld001_E_PU_P32", "RelativeLocation": {"X": -18200.0, "Y": -119140.0, "Z": 5301.0}}, {"GatherPointId": 100011101, "GatherPointTag": "P33", "GatherPointKey": "fld001_E_PU_P33", "RelativeLocation": {"X": -33605.0, "Y": -106207.0, "Z": 4932.0}}, {"GatherPointId": 100011101, "GatherPointTag": "P34", "GatherPointKey": "fld001_E_PU_P34", "RelativeLocation": {"X": -42530.0, "Y": -73680.0, "Z": 6106.0}}, {"GatherPointId": 100011101, "GatherPointTag": "P35", "GatherPointKey": "fld001_E_PU_P35", "RelativeLocation": {"X": -45710.0, "Y": -112270.0, "Z": 5056.0}}, {"GatherPointId": 100011101, "GatherPointTag": "P36", "GatherPointKey": "fld001_E_PU_P36", "RelativeLocation": {"X": -1425.0, "Y": -107538.0, "Z": 6632.0}}, {"GatherPointId": 100011101, "GatherPointTag": "P37", "GatherPointKey": "fld001_E_PU_P37", "RelativeLocation": {"X": 28927.0, "Y": -113118.0, "Z": 11428.0}}, {"GatherPointId": 100011101, "GatherPointTag": "P38", "GatherPointKey": "fld001_E_PU_P38", "RelativeLocation": {"X": 12617.0, "Y": -111952.0, "Z": 8381.0}}, {"GatherPointId": 100011101, "GatherPointTag": "P39", "GatherPointKey": "fld001_E_PU_P39", "RelativeLocation": {"X": -31384.0, "Y": -106068.0, "Z": 4679.0}}, {"GatherPointId": 100011101, "GatherPointTag": "P4", "GatherPointKey": "fld001_E_PU_P4", "RelativeLocation": {"X": -36350.0, "Y": -92240.0, "Z": 5710.0}}, {"GatherPointId": 100011101, "GatherPointTag": "P40", "GatherPointKey": "fld001_E_PU_P40", "RelativeLocation": {"X": -44051.0, "Y": -113677.0, "Z": 4659.0}}, {"GatherPointId": 100011101, "GatherPointTag": "P41", "GatherPointKey": "fld001_E_PU_P41", "RelativeLocation": {"X": -33021.0, "Y": -97687.0, "Z": 6182.0}}, {"GatherPointId": 100011101, "GatherPointTag": "P42", "GatherPointKey": "fld001_E_PU_P42", "RelativeLocation": {"X": 6604.0, "Y": -83908.0, "Z": 2246.0}}, {"GatherPointId": 100011101, "GatherPointTag": "P43", "GatherPointKey": "fld001_E_PU_P43", "RelativeLocation": {"X": 22526.0, "Y": -94296.0, "Z": 1011.0}}, {"GatherPointId": 100011101, "GatherPointTag": "P44", "GatherPointKey": "fld001_E_PU_P44", "RelativeLocation": {"X": 28894.0, "Y": -140167.0, "Z": 4875.0}}, {"GatherPointId": 100011101, "GatherPointTag": "P45", "GatherPointKey": "fld001_E_PU_P45", "RelativeLocation": {"X": 10644.0, "Y": -93777.0, "Z": 5516.0}}, {"GatherPointId": 100011101, "GatherPointTag": "P46", "GatherPointKey": "fld001_E_PU_P46", "RelativeLocation": {"X": 7934.0, "Y": -82007.0, "Z": 2356.0}}, {"GatherPointId": 100011101, "GatherPointTag": "P5", "GatherPointKey": "fld001_E_PU_P5", "RelativeLocation": {"X": -40200.0, "Y": -99270.0, "Z": 5683.0}}, {"GatherPointId": 100011101, "GatherPointTag": "P6", "GatherPointKey": "fld001_E_PU_P6", "RelativeLocation": {"X": -8470.0, "Y": -95040.0, "Z": 5062.0}}, {"GatherPointId": 100011101, "GatherPointTag": "P7", "GatherPointKey": "fld001_E_PU_P7", "RelativeLocation": {"X": -24770.0, "Y": -73720.0, "Z": 4333.0}}, {"GatherPointId": 100011101, "GatherPointTag": "P8", "GatherPointKey": "fld001_E_PU_P8", "RelativeLocation": {"X": -21259.0, "Y": -91003.0, "Z": 5410.0}}, {"GatherPointId": 100011101, "GatherPointTag": "P9", "GatherPointKey": "fld001_E_PU_P9", "RelativeLocation": {"X": 9420.0, "Y": -121200.0, "Z": 9712.0}}, {"GatherPointId": 100011102, "GatherPointTag": "P_Fix02", "GatherPointKey": "fld001_E_PU_P_Fix02", "RelativeLocation": {"X": 3492.0, "Y": -117196.0, "Z": 8809.0}}, {"GatherPointId": 100011103, "GatherPointTag": "P_Fix03", "GatherPointKey": "fld001_E_PU_P_Fix03", "RelativeLocation": {"X": -26356.0, "Y": -122757.0, "Z": 6346.0}}, {"GatherPointId": 100011104, "GatherPointTag": "P_Fix04", "GatherPointKey": "fld001_E_PU_P_Fix04", "RelativeLocation": {"X": 15285.0, "Y": -104007.0, "Z": 2021.0}}, {"GatherPointId": 100011105, "GatherPointTag": "P_Fix05", "GatherPointKey": "fld001_E_PU_P_Fix05", "RelativeLocation": {"X": 3772.0, "Y": -75804.0, "Z": 3020.0}}]